easy_scraper/__init__.py
easy_scraper/entity/__init__.py
easy_scraper/htmlparser.py
easy_scraper/matching.py
easy_scraper_py-1.0.0.dist-info/LICENSE
easy_scraper_py-1.0.0.dist-info/WHEEL
easy_scraper_py-1.0.0.dist-info/METADATA
easy_scraper_py-1.0.0.dist-info/RECORD
