Metadata-Version: 2.1
Name: easy-scraper-py
Version: 1.0.0
Summary: An Easy Scraper for HTML
Home-page: https://github.com/cympfh/easy-scraper-py/
License: MIT
Author: cympfh
Author-email: cympfh@gmail.com
Requires-Python: >=3.9,<4.0
Classifier: License :: OSI Approved :: MIT License
Classifier: Programming Language :: Python :: 3
Classifier: Programming Language :: Python :: 3.10
Classifier: Programming Language :: Python :: 3.9
Project-URL: Repository, https://github.com/cympfh/easy-scraper-py/
